EasyCalculator/EasyCalculator.py
EasyCalculator/__init__.py
EasyCalculator-0.1.11.dist-info/LICENSE.rst
EasyCalculator-0.1.11.dist-info/METADATA
EasyCalculator-0.1.11.dist-info/WHEEL
EasyCalculator-0.1.11.dist-info/top_level.txt
EasyCalculator-0.1.11.dist-info/RECORD
