Metadata-Version: 2.1
Name: EasyCalculator
Version: 0.1.11
Summary: Simple and Easy Calculator
Home-page: https://github.com/you/your_package
Author: Supriya Satyappanavar
Author-email: supriya06ms@gmail.com
License: Apache License 2.0
Platform: UNKNOWN
